pycheeg/__init__.py
pycheeg/cheeger.py
pycheeg/cheeger_trevisan.py
pycheeg-0.1.0.dist-info/LICENSE
pycheeg-0.1.0.dist-info/METADATA
pycheeg-0.1.0.dist-info/WHEEL
pycheeg-0.1.0.dist-info/top_level.txt
pycheeg-0.1.0.dist-info/RECORD
